tap_cea_googlesheet/__init__.py
tap_cea_googlesheet/client.py
tap_cea_googlesheet/schemas/schema_metadata.json
tap_cea_googlesheet/streams.py
tap_cea_googlesheet/tap.py
tap_cea_googlesheet/tests/__init__.py
tap_cea_googlesheet/tests/test_core.py
tap_cea_googlesheet-0.0.4.dist-info/entry_points.txt
tap_cea_googlesheet-0.0.4.dist-info/WHEEL
tap_cea_googlesheet-0.0.4.dist-info/METADATA
tap_cea_googlesheet-0.0.4.dist-info/RECORD
